README.md
setup.py
tpk4170/__init__.py
tpk4170.egg-info/PKG-INFO
tpk4170.egg-info/SOURCES.txt
tpk4170.egg-info/dependency_links.txt
tpk4170.egg-info/requires.txt
tpk4170.egg-info/top_level.txt
tpk4170/camera_calibration/__init__.py
tpk4170/exercises/__init__.py
tpk4170/exercises/exercise_6/__init__.py
tpk4170/exercises/exercise_6/exercise_6.py
tpk4170/forward_kinematics/__init__.py
tpk4170/forward_kinematics/forward_kinematics.py
tpk4170/hand_eye_calibration/__init__.py
tpk4170/hand_eye_calibration/chessboard.py
tpk4170/hand_eye_calibration/hand_eye_calibration.py
tpk4170/hand_eye_calibration/park_martin.py
tpk4170/hand_eye_calibration/run_calibration.py
tpk4170/hand_eye_calibration/utils.py
tpk4170/image_formation/__init__.py
tpk4170/image_formation/camera.py
tpk4170/inverse_kinematics/__init__.py
tpk4170/inverse_kinematics/inverse_kinematics.py
tpk4170/models/__init__.py
tpk4170/models/models.py
tpk4170/models/kr16_2/__init__.py
tpk4170/models/kr16_2/visual/base_link.dae
tpk4170/models/kr16_2/visual/link_1.dae
tpk4170/models/kr16_2/visual/link_2.dae
tpk4170/models/kr16_2/visual/link_3.dae
tpk4170/models/kr16_2/visual/link_4.dae
tpk4170/models/kr16_2/visual/link_5.dae
tpk4170/models/kr16_2/visual/link_6.dae
tpk4170/models/kr6r900sixx/__init__.py
tpk4170/models/kr6r900sixx/kr6r900sixx.py
tpk4170/models/kr6r900sixx/visual/base_link.dae
tpk4170/models/kr6r900sixx/visual/link_1.dae
tpk4170/models/kr6r900sixx/visual/link_2.dae
tpk4170/models/kr6r900sixx/visual/link_3.dae
tpk4170/models/kr6r900sixx/visual/link_4.dae
tpk4170/models/kr6r900sixx/visual/link_5.dae
tpk4170/models/kr6r900sixx/visual/link_6.dae
tpk4170/models/ur5/__init__.py
tpk4170/models/ur5/ur5.py
tpk4170/models/ur5/visual/base.dae
tpk4170/models/ur5/visual/forearm.dae
tpk4170/models/ur5/visual/shoulder.dae
tpk4170/models/ur5/visual/upperarm.dae
tpk4170/models/ur5/visual/wrist1.dae
tpk4170/models/ur5/visual/wrist2.dae
tpk4170/models/ur5/visual/wrist3.dae
tpk4170/pose_estimation/__init__.py
tpk4170/pose_estimation/p3p.py
tpk4170/rigid_body_motions/__init__.py
tpk4170/rigid_body_motions/rotations.py
tpk4170/trajectory_planning/__init__.py
